{
  "required": true,
  "minVersion": "0.8",
  "package": "com.miskatonicmysteries.mixin",
  "compatibilityLevel": "JAVA_8",
  "mixins": [
    "BlockMixin",
    "CropMixin",
    "DataLoadMixin",
    "ItemMixin",
    "LivingEntityAccessor",
    "LivingEntityMixin",
    "PlayerManagerMixin",
    "PlayerMixin",
    "ServerPlayerMixin",
    "ZombieVillagerAccessor",
    "villagers.ActivityAccessor",
    "villagers.MemoryModuleTypeAccessor",
    "villagers.VillagerEntityAccessor",
    "world.OceanMonumentMixin",
    "world.StructurePoolAccessor",
    "world.StructurePoolRegistryMixin"
  ],
  "client": [
    "client.ClientPlayNetworkHandlerMixin",
    "client.ParticleManagerMixin",
    "client.PlayerModelMixin"
  ],
  "injectors": {
    "defaultRequire": 1
  }
}
