{
	"required": true,
	"minVersion": "0.8",
	"package": "com.miskatonicmysteries.mixin",
	"compatibilityLevel": "JAVA_8",
	"mixins": [
		"client.ClientEntityMixin",
		"client.ClientPlayerEntityMixin",
		"client.InventoryScreenMixin",
		"client.LightmapTextureManagerMixin",
		"client.LivingEntityRendererMixin",
		"client.MobEntityRendererMixin",
		"client.ParticleManagerMixin",
		"client.PlayerModelMixin",
		"client.PlayerEntityRendererMixin",
		"client.PlayerSkinTextureAccessor",
		"client.SocialInteractionsManagerAccessor",
		"client.WorldRendererAccessor",
		"client.WorldRendererMixin"
	],
	"injectors": {
		"defaultRequire": 1
	}
}
